lyscripts/__init__.py
lyscripts/__main__.py
lyscripts/_version.py
lyscripts/cli.py
lyscripts/configs.py
lyscripts/decorators.py
lyscripts/evaluate.py
lyscripts/integrate.py
lyscripts/plots.py
lyscripts/sample.py
lyscripts/schedule.py
lyscripts/schema.py
lyscripts/utils.py
lyscripts/compute/__init__.py
lyscripts/compute/__main__.py
lyscripts/compute/evidence.py
lyscripts/compute/posteriors.py
lyscripts/compute/prevalences.py
lyscripts/compute/priors.py
lyscripts/compute/risks.py
lyscripts/compute/utils.py
lyscripts/data/__init__.py
lyscripts/data/__main__.py
lyscripts/data/enhance.py
lyscripts/data/fetch.py
lyscripts/data/filter.py
lyscripts/data/generate.py
lyscripts/data/join.py
lyscripts/data/lyproxify.py
lyscripts/data/split.py
lyscripts/data/utils.py
lyscripts/data/collect/__init__.py
lyscripts/data/collect/collector.js
lyscripts/data/collect/index.html
lyscripts-1.0.1.dist-info/licenses/LICENSE
lyscripts-1.0.1.dist-info/METADATA
lyscripts-1.0.1.dist-info/WHEEL
lyscripts-1.0.1.dist-info/entry_points.txt
lyscripts-1.0.1.dist-info/top_level.txt
lyscripts-1.0.1.dist-info/RECORD
