Metadata-Version: 2.4
Name: lyscripts
Version: 1.0.1
Summary: Package to interact with lymphatic progression data and models.
Author-email: Roman Ludwig <roman.ludwig@usz.ch>
License: MIT
Project-URL: source, https://github.com/lycosystem/lyscripts
Project-URL: documentation, https://lyscripts.readthedocs.io
Keywords: scripts,lymph,inference
Classifier: Development Status :: 4 - Beta
Classifier: Intended Audience :: Developers
Classifier: Intended Audience :: Science/Research
Classifier: License :: OSI Approved :: MIT License
Classifier: Natural Language :: English
Classifier: Programming Language :: Python
Classifier: Programming Language :: Python :: 3
Classifier: Programming Language :: Python :: 3.10
Classifier: Programming Language :: Python :: 3.11
Classifier: Programming Language :: Python :: 3.12
Classifier: Programming Language :: Python :: 3.13
Classifier: Topic :: Scientific/Engineering
Classifier: Topic :: Software Development :: Libraries
Requires-Python: >=3.10
License-File: LICENSE
Requires-Dist: numpy
Requires-Dist: pandas
Requires-Dist: emcee
Requires-Dist: h5py
Requires-Dist: tables
Requires-Dist: matplotlib
Requires-Dist: corner
Requires-Dist: scipy
Requires-Dist: xlrd
Requires-Dist: rich
Requires-Dist: rich-argparse
Requires-Dist: pyyaml
Requires-Dist: lymph-model>=1.3.3
Requires-Dist: deprecated
Requires-Dist: joblib
Requires-Dist: pydantic
Requires-Dist: pydantic-settings!=2.9.0,!=2.9.1,>=2.7.0
Requires-Dist: numpydantic
Requires-Dist: loguru
Requires-Dist: fastapi
Requires-Dist: uvicorn
Requires-Dist: lydata>=0.4.0
Provides-Extra: docs
Requires-Dist: sphinx; extra == "docs"
Requires-Dist: sphinx-book-theme; extra == "docs"
Requires-Dist: sphinx-autodoc-typehints; extra == "docs"
Requires-Dist: sphinxcontrib-programoutput; extra == "docs"
Requires-Dist: myst_parser; extra == "docs"
Requires-Dist: autodoc_pydantic; extra == "docs"
Provides-Extra: tests
Requires-Dist: pytest; extra == "tests"
Requires-Dist: pytest-cov; extra == "tests"
Requires-Dist: pytest-mpl; extra == "tests"
Provides-Extra: dev
Requires-Dist: pre-commit; extra == "dev"
Requires-Dist: git-cliff; extra == "dev"
Dynamic: license-file
